sqlmeta/__init__.py
sqlmeta/base.py
sqlmeta/adapters/__init__.py
sqlmeta/adapters/alembic.py
sqlmeta/adapters/pydantic.py
sqlmeta/adapters/sqlalchemy.py
sqlmeta/comparison/__init__.py
sqlmeta/comparison/comparator.py
sqlmeta/comparison/diff_models.py
sqlmeta/comparison/type_normalizer.py
sqlmeta/objects/__init__.py
sqlmeta/objects/database_link.py
sqlmeta/objects/event.py
sqlmeta/objects/extension.py
sqlmeta/objects/foreign_data_wrapper.py
sqlmeta/objects/foreign_server.py
sqlmeta/objects/index.py
sqlmeta/objects/linked_server.py
sqlmeta/objects/module.py
sqlmeta/objects/package.py
sqlmeta/objects/partition.py
sqlmeta/objects/procedure.py
sqlmeta/objects/sequence.py
sqlmeta/objects/synonym.py
sqlmeta/objects/table.py
sqlmeta/objects/trigger.py
sqlmeta/objects/user_defined_type.py
sqlmeta/objects/view.py
sqlmeta/utils/__init__.py
sqlmeta-0.1.0.dist-info/licenses/LICENSE
sqlmeta-0.1.0.dist-info/METADATA
sqlmeta-0.1.0.dist-info/WHEEL
sqlmeta-0.1.0.dist-info/top_level.txt
sqlmeta-0.1.0.dist-info/RECORD
