Metadata-Version: 2.4
Name: sqlmeta
Version: 0.1.0
Summary: Universal SQL metadata and schema representation for Python
Author-email: Your Name <your@email.com>
License: MIT
Project-URL: Homepage, https://github.com/cmodiano/sqlmeta
Project-URL: Documentation, https://sqlmeta.readthedocs.io
Project-URL: Repository, https://github.com/cmodiano/sqlmeta
Project-URL: Issues, https://github.com/cmodiano/sqlmeta/issues
Keywords: sql,schema,metadata,database,orm,sqlalchemy,pydantic,postgresql,mysql,oracle,sqlserver
Classifier: Development Status :: 4 - Beta
Classifier: Intended Audience :: Developers
Classifier: License :: OSI Approved :: MIT License
Classifier: Programming Language :: Python :: 3
Classifier: Programming Language :: Python :: 3.8
Classifier: Programming Language :: Python :: 3.9
Classifier: Programming Language :: Python :: 3.10
Classifier: Programming Language :: Python :: 3.11
Classifier: Programming Language :: Python :: 3.12
Classifier: Topic :: Database
Classifier: Topic :: Software Development :: Libraries :: Python Modules
Classifier: Typing :: Typed
Requires-Python: >=3.8
License-File: LICENSE
Provides-Extra: sqlalchemy
Requires-Dist: sqlalchemy>=1.4; extra == "sqlalchemy"
Provides-Extra: pydantic
Requires-Dist: pydantic>=2.0; extra == "pydantic"
Provides-Extra: alembic
Requires-Dist: alembic>=1.7; extra == "alembic"
Provides-Extra: dev
Requires-Dist: pytest>=7.0; extra == "dev"
Requires-Dist: pytest-cov>=4.0; extra == "dev"
Requires-Dist: black>=23.0; extra == "dev"
Requires-Dist: mypy>=1.0; extra == "dev"
Requires-Dist: ruff>=0.1.0; extra == "dev"
Provides-Extra: all
Requires-Dist: sqlalchemy>=1.4; extra == "all"
Requires-Dist: pydantic>=2.0; extra == "all"
Requires-Dist: alembic>=1.7; extra == "all"
Dynamic: license-file
